curl_adapter/__init__.py
curl_adapter/base_adapter.py
curl_adapter/curl_cffi.py
curl_adapter/pycurl.py
curl_adapter/stream/handler.py
curl_adapter/stream/response.py
curl_adapter-1.0.0.post3.dist-info/LICENSE
curl_adapter-1.0.0.post3.dist-info/METADATA
curl_adapter-1.0.0.post3.dist-info/WHEEL
curl_adapter-1.0.0.post3.dist-info/top_level.txt
curl_adapter-1.0.0.post3.dist-info/RECORD
