Metadata-Version: 2.1
Name: curl_adapter
Version: 1.0.0.post3
Summary: A curl HTTP adapter switch for requests library — make browser-like requests with custom TLS fingerprints.
Author-email: "Elis K." <github@elis.cc>
License: MIT License
Project-URL: Homepage, https://github.com/el1s7/curl-adapter
Keywords: curl,requests,adapter,tls fingerprint,pycurl,curl_cffi,curl impersonate
Requires-Python: >=3.8
License-File: LICENSE
Requires-Dist: requests
Requires-Dist: curl-cffi
Requires-Dist: pycurl ==7.45.3
Provides-Extra: test
Requires-Dist: pytest ; extra == 'test'
